SLACplots/__init__.py
SLACplots/colors.py
SLACplots/latex.py
SLACplots/rcparams.py
SLACplots/stanford.py
slacplots-1.0.2.dist-info/licenses/LICENSE
slacplots-1.0.2.dist-info/METADATA
slacplots-1.0.2.dist-info/WHEEL
slacplots-1.0.2.dist-info/top_level.txt
slacplots-1.0.2.dist-info/RECORD
