Metadata-Version: 2.4
Name: SLACplots
Version: 1.0.2
Summary: Plotting utilities for matplotlib in the SLAC style
Home-page: https://github.com/DanielMDouglas/SLACplots
Author: Daniel Douglas
Author-email: dougl215@slac.stanford.edu
Classifier: Development Status :: 5 - Production/Stable
Classifier: Intended Audience :: Developers
Classifier: License :: OSI Approved :: MIT License
Classifier: Operating System :: OS Independent
Classifier: Programming Language :: Python :: 3
Classifier: Topic :: Scientific/Engineering :: Physics
Requires-Python: >=3.2
License-File: LICENSE
Requires-Dist: matplotlib
Dynamic: author
Dynamic: author-email
Dynamic: classifier
Dynamic: home-page
Dynamic: license-file
Dynamic: requires-dist
Dynamic: requires-python
Dynamic: summary
